LICENSE
README.md
zdppy_orm/__init__.py
zdppy_orm/model.py
zdppy_orm/mysql_ext.py
zdppy_orm/pool.py
zdppy_orm/shortcuts.py
zdppy_orm-0.1.4.dist-info/LICENSE
zdppy_orm-0.1.4.dist-info/WHEEL
zdppy_orm-0.1.4.dist-info/METADATA
zdppy_orm-0.1.4.dist-info/RECORD
